email_address_local/__init__.py
email_address_local/email_address.py
email_address_local/email_address_constants_src.py
email_address_local-0.0.65.dist-info/METADATA
email_address_local-0.0.65.dist-info/WHEEL
email_address_local-0.0.65.dist-info/top_level.txt
email_address_local-0.0.65.dist-info/RECORD
